pluginsmanager/__init__.py
pluginsmanager/banks_manager.py
pluginsmanager/jack/__init__.py
pluginsmanager/jack/jack_client.py
pluginsmanager/jack/jack_interface.py
pluginsmanager/model/__init__.py
pluginsmanager/model/audio_port.py
pluginsmanager/model/bank.py
pluginsmanager/model/connection.py
pluginsmanager/model/connections_list.py
pluginsmanager/model/effect.py
pluginsmanager/model/effects_list.py
pluginsmanager/model/input.py
pluginsmanager/model/midi_connection.py
pluginsmanager/model/midi_input.py
pluginsmanager/model/midi_output.py
pluginsmanager/model/midi_port.py
pluginsmanager/model/output.py
pluginsmanager/model/param.py
pluginsmanager/model/pedalboard.py
pluginsmanager/model/port.py
pluginsmanager/model/lv2/__init__.py
pluginsmanager/model/lv2/lilvlib.py
pluginsmanager/model/lv2/lv2_effect.py
pluginsmanager/model/lv2/lv2_effect_builder.py
pluginsmanager/model/lv2/lv2_input.py
pluginsmanager/model/lv2/lv2_midi_input.py
pluginsmanager/model/lv2/lv2_midi_output.py
pluginsmanager/model/lv2/lv2_output.py
pluginsmanager/model/lv2/lv2_param.py
pluginsmanager/model/lv2/lv2_plugin.py
pluginsmanager/model/lv2/lv2_port_mixing.py
pluginsmanager/model/lv2/plugins.json
pluginsmanager/model/system/__init__.py
pluginsmanager/model/system/system_effect.py
pluginsmanager/model/system/system_effect_builder.py
pluginsmanager/model/system/system_input.py
pluginsmanager/model/system/system_midi_input.py
pluginsmanager/model/system/system_midi_output.py
pluginsmanager/model/system/system_output.py
pluginsmanager/model/system/system_port_mixing.py
pluginsmanager/observer/__init__.py
pluginsmanager/observer/observable_list.py
pluginsmanager/observer/observer_manager.py
pluginsmanager/observer/scope.py
pluginsmanager/observer/update_type.py
pluginsmanager/observer/updates_observer.py
pluginsmanager/observer/autosaver/__init__.py
pluginsmanager/observer/autosaver/autosaver.py
pluginsmanager/observer/autosaver/banks_files.py
pluginsmanager/observer/autosaver/index_file.py
PedalPi_PluginsManager-0.8.0.dist-info/LICENSE
PedalPi_PluginsManager-0.8.0.dist-info/METADATA
PedalPi_PluginsManager-0.8.0.dist-info/WHEEL
PedalPi_PluginsManager-0.8.0.dist-info/top_level.txt
PedalPi_PluginsManager-0.8.0.dist-info/RECORD
