Metadata-Version: 2.1
Name: PedalPi-PluginsManager
Version: 0.8.0
Summary: Pythonic management of LV2 audio plugins with mod-host.
Home-page: https://github.com/PedalPi/PluginsManager
Author: Paulo Mateus Moura da Silva (SrMouraSilva)
Author-email: mateus.moura@hotmail.com
Maintainer: Paulo Mateus Moura da Silva (SrMouraSilva)
Maintainer-email: mateus.moura@hotmail.com
License: Apache Software License v2
Keywords: pedal-pi mod-host lv2 audio plugins-manager carla
Platform: Linux
Classifier: Development Status :: 4 - Beta
Classifier: Intended Audience :: Developers
Classifier: License :: OSI Approved :: Apache Software License
Classifier: Topic :: Multimedia :: Sound/Audio
Classifier: Programming Language :: Python :: 3.5
Classifier: Programming Language :: Python :: 3.6
Classifier: Programming Language :: Python :: 3.7
Classifier: Programming Language :: Python :: 3.8
Requires-Dist: JACK-Client
Requires-Dist: pyaudio
